peegy/__init__.py
peegy/definitions/__init__.py
peegy/definitions/channel_definitions.py
peegy/definitions/default_paths.py
peegy/definitions/edf_bdf_reader.py
peegy/definitions/eegReaderAbstractClasses.py
peegy/definitions/eeg_definitions.py
peegy/definitions/events.py
peegy/definitions/tables.py
peegy/directories/__init__.py
peegy/directories/tools.py
peegy/io/__init__.py
peegy/io/data_repositories/dropbox/tools.py
peegy/io/eeg/__init__.py
peegy/io/eeg/reader.py
peegy/io/exporters/__init__.py
peegy/io/exporters/bids_tools.py
peegy/io/exporters/edf_bdf_writer.py
peegy/io/exporters/wav_writer.py
peegy/io/external_tools/__init__.py
peegy/io/external_tools/file_tools.py
peegy/io/external_tools/aep_gui/__init__.py
peegy/io/external_tools/aep_gui/aep_matlab_tools.py
peegy/io/external_tools/aep_gui/dataReadingTools.py
peegy/io/external_tools/aep_gui/extsys_tools.py
peegy/io/external_tools/aep_gui/medel_stimuli_reader.py
peegy/io/paths/defaults.py
peegy/io/readers/__init__.py
peegy/io/readers/eclipse_tools.py
peegy/io/readers/edf_bdf_reader.py
peegy/io/readers/generic_csv_reader.py
peegy/io/readers/synergy_reader.py
peegy/io/storage/__init__.py
peegy/io/storage/data_storage_reading_tools.py
peegy/io/storage/data_storage_tools.py
peegy/io/storage/plot_tools.py
peegy/io/tools/__init__.py
peegy/io/tools/xml_tools.py
peegy/layouts/KIT-160.lay
peegy/layouts/__init__.py
peegy/layouts/biosemi128.lay
peegy/layouts/biosemi16.lay
peegy/layouts/biosemi160.lay
peegy/layouts/biosemi256.lay
peegy/layouts/biosemi32.lay
peegy/layouts/biosemi32_2_EXT.lay
peegy/layouts/biosemi32_fnirs_MP.lay
peegy/layouts/biosemi32_fnirs_jaime.lay
peegy/layouts/biosemi64.lay
peegy/layouts/biosemi64_2_EXT.lay
peegy/layouts/biosemi64_3_EXT.lay
peegy/layouts/brainvision64.bvef
peegy/layouts/emotive14.lay
peegy/layouts/layouts.py
peegy/layouts/neuroscan64.lay
peegy/plot/__init__.py
peegy/plot/eeg_ave_epochs_plot_tools.py
peegy/plot/eeg_plot_tools.py
peegy/processing/__init__.py
peegy-1.6.1.dist-info/METADATA
peegy-1.6.1.dist-info/WHEEL
peegy-1.6.1.dist-info/licenses/LICENSE.txt
peegy-1.6.1.dist-info/RECORD
