Metadata-Version: 2.4
Name: peegy
Version: 1.6.1
Summary: Tools to pipeline bulk analyses of EEG and other modalities.
Project-URL: Homepage, https://gitlab.com/open-source-brain/peegy/
Project-URL: Examples, https://open-source-brain.gitlab.io/peegy/
Author-email: Jaime Undurraga <jaime.undurraga@gmail.com>
License: MIT
License-File: LICENSE.txt
Classifier: Development Status :: 3 - Alpha
Classifier: Environment :: Console
Classifier: Intended Audience :: Science/Research
Classifier: Operating System :: MacOS :: MacOS X
Classifier: Operating System :: Microsoft :: Windows :: Windows 10
Classifier: Operating System :: POSIX :: Linux
Classifier: Programming Language :: Python :: 3
Classifier: Topic :: Scientific/Engineering :: Bio-Informatics
Requires-Python: >=3.9
Requires-Dist: astropy>=5.2.1
Requires-Dist: bidshandler>=0.2.1
Requires-Dist: cython>=0.29.33
Requires-Dist: dropbox>=12.0.2
Requires-Dist: fire>=0.5.0
Requires-Dist: gitpython>=3.1.31
Requires-Dist: graphviz>=0.20.1
Requires-Dist: h5py>=3.8.0
Requires-Dist: joblib>=1.2.0
Requires-Dist: lxml>=4.9.2
Requires-Dist: matplotlib<=3.9.0
Requires-Dist: numba-progress>=0.0.4
Requires-Dist: numba>=0.56.4
Requires-Dist: numpy>=2.0.0
Requires-Dist: opencv-python-headless>=4.12.0.88
Requires-Dist: pandas>=2.3.3
Requires-Dist: pillow>=9.4.0
Requires-Dist: prettytable>=3.7.0
Requires-Dist: psutil>=5.9.5
Requires-Dist: pydot>=1.4.2
Requires-Dist: pyedflib>=0.1.32
Requires-Dist: pyfftw>=0.13.1
Requires-Dist: pyqt5-stubs>=5.15.6.0
Requires-Dist: pyqt5>=5.15.9
Requires-Dist: pyqtgraph>=0.13.3
Requires-Dist: pywavelets>=1.4.1
Requires-Dist: qt5-py>=0.1.0
Requires-Dist: ray>=2.0.1
Requires-Dist: scikit-learn>=1.2.2
Requires-Dist: scipy>=1.16.3
Requires-Dist: seaborn>=0.13.2
Requires-Dist: soundfile>=0.12.1
Requires-Dist: sqlalchemy>=2.0.45
Requires-Dist: ssqueezepy>=0.6.4
Requires-Dist: tabulate>=0.9.0
Requires-Dist: toml>=0.10.2
Requires-Dist: tqdm>=4.64.1
